7eaee132373d5bf56d84__mypyc.cpython-314-darwin.so
eth_event-1.4.4.dist-info/RECORD
eth_event-1.4.4.dist-info/WHEEL
eth_event-1.4.4.dist-info/top_level.txt
eth_event-1.4.4.dist-info/METADATA
eth_event-1.4.4.dist-info/licenses/LICENSE
eth_event/__init__.cpython-314-darwin.so
eth_event/__init__.py
eth_event/main.cpython-314-darwin.so
eth_event/py.typed
eth_event/main.py
