Metadata-Version: 2.1
Name: eth-event
Version: 1.4.4
Summary: Ethereum event decoder and topic generator
Home-page: https://github.com/iamdefinitelyahuman/eth-event
Author: Benjamin Hauser
Author-email: ben@hauser.id
License: MIT
Keywords: ethereum
Classifier: Development Status :: 5 - Production/Stable
Classifier: Intended Audience :: Developers
Classifier: Topic :: Software Development :: Build Tools
Classifier: License :: OSI Approved :: MIT License
Classifier: Programming Language :: Python :: 3
Classifier: Programming Language :: Python :: 3.9
Classifier: Programming Language :: Python :: 3.10
Classifier: Programming Language :: Python :: 3.11
Classifier: Programming Language :: Python :: 3.12
Classifier: Programming Language :: Python :: 3.13
Classifier: Programming Language :: Python :: 3.14
Requires-Python: >=3.9,<4
License-File: LICENSE
